CHANGELOG.txt
LICENSE
MANIFEST.in
README.md
requirements.txt
setup.py
test.py
todo.txt
DarwinPy/__init__.py
DarwinPy.egg-info/PKG-INFO
DarwinPy.egg-info/SOURCES.txt
DarwinPy.egg-info/dependency_links.txt
DarwinPy.egg-info/requires.txt
DarwinPy.egg-info/top_level.txt
DarwinPy/Core/__init__.py
DarwinPy/EvolutionaryStrategy/__init__.py
DarwinPy/Functions/__init__.py
DarwinPy/Genetics/__init__.py
DarwinPy/Utils/__init__.py