Metadata-Version: 2.1
Name: DarwinPy
Version: 0.0.2
Summary: A evolutionary computation module
Home-page: UNKNOWN
Author: Pius Arhanbhunde
Author-email: pjacks419@gmail.com
License: MIT License
Keywords: evolution
Platform: UNKNOWN
Classifier: Development Status :: 5 - Production/Stable
Classifier: Intended Audience :: Developers
Classifier: Operating System :: Microsoft :: Windows :: Windows 10
Classifier: License :: OSI Approved :: MIT License
Classifier: Programming Language :: Python :: 3
License-File: LICENSE
